firebase_remote_config/__init__.py
firebase_remote_config/client.py
firebase_remote_config/exceptions.py
firebase_remote_config/models.py
firebase_remote_config/conditions/__init__.py
firebase_remote_config/conditions/builder.py
firebase_remote_config/conditions/conditions.py
firebase_remote_config/conditions/enums.py
firebase_remote_config/conditions/parser.py
firebase_remote_config/conditions/validation.py
firebase_remote_config-0.1.22.dist-info/licenses/LICENSE
firebase_remote_config-0.1.22.dist-info/METADATA
firebase_remote_config-0.1.22.dist-info/WHEEL
firebase_remote_config-0.1.22.dist-info/top_level.txt
firebase_remote_config-0.1.22.dist-info/RECORD
