Metadata-Version: 2.4
Name: firebase-remote-config
Version: 0.1.22
Summary: Firebase Remote Config SDK
Author-email: Dmitry Kaysin <kaysin.dmitry@gmail.com>
Project-URL: Homepage, https://github.com/apprevenew-com/firebase-remote-config-python
Project-URL: Issues, https://github.com/apprevenew-com/firebase-remote-config-python/issues
Keywords: firebase,remote,config
Requires-Python: >=3.9
License-File: LICENSE
Requires-Dist: requests>=2.32.3
Requires-Dist: google-auth==2.38.0
Requires-Dist: pydantic>=2.10.6
Requires-Dist: pyparsing>=3.2.1
Requires-Dist: pytz==2024.1
Provides-Extra: dev
Requires-Dist: ruff==0.11.0; extra == "dev"
Requires-Dist: pytest==8.3.5; extra == "dev"
Dynamic: license-file
